distlockd/__init__.py
distlockd/__main__.py
distlockd/benchmark.py
distlockd/cli.py
distlockd/client.py
distlockd/connection_pool.py
distlockd/constants.py
distlockd/exceptions.py
distlockd/protocol.py
distlockd/server.py
distlockd-1.0.3.dist-info/licenses/LICENSE
distlockd-1.0.3.dist-info/METADATA
distlockd-1.0.3.dist-info/WHEEL
distlockd-1.0.3.dist-info/entry_points.txt
distlockd-1.0.3.dist-info/top_level.txt
distlockd-1.0.3.dist-info/RECORD
